{
  "code": 200,
  "message": "OK",
  "data": {
    "playerId": "MarketUpdater",
    "updated": "03/12/2024",
    "comment": "Market created by MarketUpdater",
    "developer": "essence#0001",
    "inventory": [
      {
        "lastUpdatedAt": 1710259975,
        "objectId": "Dwight",
        "quantity": 1
      },
      {
        "lastUpdatedAt": 1710259975,
        "objectId": "Meg",
        "quantity": 1
      },
      {
        "lastUpdatedAt": 1710259975,
        "objectId": "Claudette",
        "quantity": 1
      },
      {
        "lastUpdatedAt": 1710259975,
        "objectId": "Chuckles",
        "quantity": 1
      },
      {
        "lastUpdatedAt": 1710259975,
        "objectId": "Bob",
        "quantity": 1
      },
      {
        "lastUpdatedAt": 1710259975,
        "objectId": "Cannibal",
        "quantity": 1
      },
      {
        "lastUpdatedAt": 1710259975,
        "objectId": "HillBilly",
        "quantity": 1
      },
      {
        "lastUpdatedAt": 1710259975,
        "objectId": "Witch",
        "quantity": 1
      },
      {
        "lastUpdatedAt": 1710259975,
        "objectId": "Jake",
        "quantity": 1
      },
      {
        "lastUpdatedAt": 1710259975,
        "objectId": "Nea",
        "quantity": 1
      },
      {
        "lastUpdatedAt": 1710259975,
        "objectId": "Ace",
        "quantity": 1
      },
      {
        "lastUpdatedAt": 1710259975,
        "objectId": "K35",
        "quantity": 1
      },
      {
        "lastUpdatedAt": 1710259975,
        "objectId": "S41",
        "quantity": 1
      },
      {
        "lastUpdatedAt": 1710259975,
        "objectId": "Ash",
        "quantity": 1
      },
      {
        "lastUpdatedAt": 1710259975,
        "objectId": "S24",
        "quantity": 1
      },
      {
        "lastUpdatedAt": 1710259975,
        "objectId": "K22",
        "quantity": 1
      },
      {
        "lastUpdatedAt": 1710259975,
        "objectId": "S25",
        "quantity": 1
      },
      {
        "lastUpdatedAt": 1710259975,
        "objectId": "K23",
        "quantity": 1
      },
      {
        "lastUpdatedAt": 1710259975,
        "objectId": "Laurie",
        "quantity": 1
      },
      {
        "lastUpdatedAt": 1710259975,
        "objectId": "Shape",
        "quantity": 1
      },
      {
        "lastUpdatedAt": 1710259975,
        "objectId": "Killer07",
        "quantity": 1
      },
      {
        "lastUpdatedAt": 1710259975,
        "objectId": "Feng",
        "quantity": 1
      },
      {
        "lastUpdatedAt": 1710259975,
        "objectId": "Bear",
        "quantity": 1
      },
      {
        "lastUpdatedAt": 1710259975,
        "objectId": "Smoke",
        "quantity": 1
      },
      {
        "lastUpdatedAt": 1710259975,
        "objectId": "K24",
        "quantity": 1
      },
      {
        "lastUpdatedAt": 1710259975,
        "objectId": "S26",
        "quantity": 1
      },
      {
        "lastUpdatedAt": 1710259975,
        "objectId": "S27",
        "quantity": 1
      },
      {
        "lastUpdatedAt": 1710259975,
        "objectId": "Nightmare",
        "quantity": 1
      },
      {
        "lastUpdatedAt": 1710259975,
        "objectId": "Quentin",
        "quantity": 1
      },
      {
        "lastUpdatedAt": 1710259975,
        "objectId": "Pig",
        "quantity": 1
      },
      {
        "lastUpdatedAt": 1710259975,
        "objectId": "Eric",
        "quantity": 1
      },
      {
        "lastUpdatedAt": 1710259975,
        "objectId": "K25",
        "quantity": 1
      },
      {
        "lastUpdatedAt": 1710259975,
        "objectId": "Kate",
        "quantity": 1
      },
      {
        "lastUpdatedAt": 1710259975,
        "objectId": "Clown",
        "quantity": 1
      },
      {
        "lastUpdatedAt": 1710259975,
        "objectId": "Adam",
        "quantity": 1
      },
      {
        "lastUpdatedAt": 1710259975,
        "objectId": "Spirit",
        "quantity": 1
      },
      {
        "lastUpdatedAt": 1710259975,
        "objectId": "S28",
        "quantity": 1
      },
      {
        "lastUpdatedAt": 1710259975,
        "objectId": "K26",
        "quantity": 1
      },
      {
        "lastUpdatedAt": 1710259975,
        "objectId": "S29",
        "quantity": 1
      },
      {
        "lastUpdatedAt": 1710259975,
        "objectId": "Jeff",
        "quantity": 1
      },
      {
        "lastUpdatedAt": 1710259975,
        "objectId": "Legion",
        "quantity": 1
      },
      {
        "lastUpdatedAt": 1710259975,
        "objectId": "K27",
        "quantity": 1
      },
      {
        "lastUpdatedAt": 1710259975,
        "objectId": "S30",
        "quantity": 1
      },
      {
        "lastUpdatedAt": 1710259975,
        "objectId": "Bill",
        "quantity": 1
      },
      {
        "lastUpdatedAt": 1710259975,
        "objectId": "Jane",
        "quantity": 1
      },
      {
        "lastUpdatedAt": 1710259975,
        "objectId": "Plague",
        "quantity": 1
      },
      {
        "lastUpdatedAt": 1710259975,
        "objectId": "K28",
        "quantity": 1
      },
      {
        "lastUpdatedAt": 1710259975,
        "objectId": "S31",
        "quantity": 1
      },
      {
        "lastUpdatedAt": 1710259975,
        "objectId": "Ghostface",
        "quantity": 1
      },
      {
        "lastUpdatedAt": 1710259975,
        "objectId": "K29",
        "quantity": 1
      },
      {
        "lastUpdatedAt": 1710259975,
        "objectId": "S32",
        "quantity": 1
      },
      {
        "lastUpdatedAt": 1710259975,
        "objectId": "S33",
        "quantity": 1
      },
      {
        "lastUpdatedAt": 1710259975,
        "objectId": "Demogorgon",
        "quantity": 1
      },
      {
        "lastUpdatedAt": 1710259975,
        "objectId": "Nancy",
        "quantity": 1
      },
      {
        "lastUpdatedAt": 1710259975,
        "objectId": "Steve",
        "quantity": 1
      },
      {
        "lastUpdatedAt": 1710259975,
        "objectId": "K30",
        "quantity": 1
      },
      {
        "lastUpdatedAt": 1710259975,
        "objectId": "S34",
        "quantity": 1
      },
      {
        "lastUpdatedAt": 1710259975,
        "objectId": "K31",
        "quantity": 1
      },
      {
        "lastUpdatedAt": 1710259975,
        "objectId": "S35",
        "quantity": 1
      },
      {
        "lastUpdatedAt": 1710259975,
        "objectId": "S36",
        "quantity": 1
      },
      {
        "lastUpdatedAt": 1710259975,
        "objectId": "Yui",
        "quantity": 1
      },
      {
        "lastUpdatedAt": 1710259975,
        "objectId": "Oni",
        "quantity": 1
      },
      {
        "lastUpdatedAt": 1710259975,
        "objectId": "Nurse",
        "quantity": 1
      },
      {
        "lastUpdatedAt": 1710259975,
        "objectId": "Zarina",
        "quantity": 1
      },
      {
        "lastUpdatedAt": 1710259975,
        "objectId": "Gunslinger",
        "quantity": 1
      },
      {
        "lastUpdatedAt": 1710259975,
        "objectId": "K32",
        "quantity": 1
      },
      {
        "lastUpdatedAt": 1710259975,
        "objectId": "S37",
        "quantity": 1
      },
      {
        "lastUpdatedAt": 1710259975,
        "objectId": "S38",
        "quantity": 1
      },
      {
        "lastUpdatedAt": 1710259975,
        "objectId": "S22",
        "quantity": 1
      },
      {
        "lastUpdatedAt": 1710259975,
        "objectId": "K20",
        "quantity": 1
      },
      {
        "lastUpdatedAt": 1710259975,
        "objectId": "K33",
        "quantity": 1
      },
      {
        "lastUpdatedAt": 1710259975,
        "objectId": "S39",
        "quantity": 1
      },
      {
        "lastUpdatedAt": 1710259975,
        "objectId": "S23",
        "quantity": 1
      },
      {
        "lastUpdatedAt": 1710259975,
        "objectId": "K21",
        "quantity": 1
      },
      {
        "lastUpdatedAt": 1710259975,
        "objectId": "K34",
        "quantity": 1
      },
      {
        "lastUpdatedAt": 1710259975,
        "objectId": "S40",
        "quantity": 1
      }
    ]
  }
}